{
	"_id": "14537247",
	"site": "http://mockrest.com/",
	"title": " MockREST – Create REST APIs from Your JSON Content",
	"author": "jventura",
	"date": "2017-06-13T10:39:02.856Z",
	"tags": [],
	"content": "mockrestcreate rest apis your json content. api token (free) fully featured rest api's, create, update delete rows your json. automatic endpointsmockrest generates endpoints automatically your json objects. can access data using http verb such get, post, put delete. each creation, update deletion is automatically inserted your json, you then access your api backend.joão ventura © 2017"
}